agent_tooling/__init__.py
agent_tooling/ollama_client.py
agent_tooling/openai_client.py
agent_tooling/tool.py
agent_tooling/tool_discovery.py
agent_tooling-0.4.6.dist-info/licenses/LICENSE
tests/__init__.py
tests/test_openai_integration.py
tests/test_tool.py
agent_tooling-0.4.6.dist-info/METADATA
agent_tooling-0.4.6.dist-info/WHEEL
agent_tooling-0.4.6.dist-info/top_level.txt
agent_tooling-0.4.6.dist-info/RECORD
