Metadata-Version: 2.4
Name: agent_tooling
Version: 0.4.6
Summary: A lightweight tool registry for function metadata management
Home-page: https://github.com/danielstewart77/agent_tooling
Author: Daniel Stewart
Author-email: Daniel Stewart <daniel.stewart77@gmail.com>
License: MIT License
Project-URL: Homepage, https://github.com/danielstewart77/agent_tooling
Project-URL: Repository, https://github.com/danielstewart77/agent_tooling
Project-URL: Bug Tracker, https://github.com/danielstewart77/agent_tooling/issues
Keywords: tools,metadata,function-registry,ai-agents
Classifier: Development Status :: 3 - Alpha
Classifier: Intended Audience :: Developers
Classifier: License :: OSI Approved :: MIT License
Classifier: Programming Language :: Python :: 3.9
Classifier: Programming Language :: Python :: 3.10
Classifier: Programming Language :: Python :: 3.11
Classifier: Programming Language :: Python :: 3.12
Classifier: Programming Language :: Python :: 3.13
Classifier: Topic :: Software Development :: Libraries :: Python Modules
Requires-Python: >=3.8
License-File: LICENSE
Provides-Extra: dev
Requires-Dist: pytest; extra == "dev"
Requires-Dist: twine; extra == "dev"
Requires-Dist: build; extra == "dev"
Requires-Dist: black; extra == "dev"
Requires-Dist: mypy; extra == "dev"
Requires-Dist: flake8; extra == "dev"
Dynamic: author
Dynamic: home-page
Dynamic: license-file
Dynamic: requires-python
